<?xml version="1.0" encoding="UTF-8"?>
<metadata xml:lang="en"><Esri><CreaDate>20211110</CreaDate><CreaTime>17133000</CreaTime><ArcGISFormat>1.0</ArcGISFormat><SyncOnce>TRUE</SyncOnce><DataProperties><lineage><Process ToolSource="c:\program files\arcgis\pro\Resources\ArcToolbox\toolboxes\Conversion Tools.tbx\RasterToASCII" Date="20211110" Time="171330">RasterToASCII Reclass_Wet_1 C:\Users\kle89686\AppData\Local\ESRI\ArcGISPro\SpatialAnalyst\WetP.asc</Process></lineage></DataProperties></Esri></metadata>
